keyoscacquire/VERSION
keyoscacquire/__init__.py
keyoscacquire/__main__.py
keyoscacquire/auxiliary.py
keyoscacquire/config.py
keyoscacquire/dataprocessing.py
keyoscacquire/fileio.py
keyoscacquire/installed_cli_programmes.py
keyoscacquire/oscacq.py
keyoscacquire/oscilloscope.py
keyoscacquire/programmes.py
keyoscacquire/traceio.py
keyoscacquire/visa_utils.py
keyoscacquire-4.0.0.dist-info/LICENSE.md
keyoscacquire-4.0.0.dist-info/METADATA
keyoscacquire-4.0.0.dist-info/WHEEL
keyoscacquire-4.0.0.dist-info/entry_points.txt
keyoscacquire-4.0.0.dist-info/top_level.txt
keyoscacquire-4.0.0.dist-info/RECORD
