Metadata-Version: 2.1
Name: keyoscacquire
Version: 4.0.0
Summary: keyoscacquire is a Python package for acquiring traces from Keysight oscilloscopes through a VISA interface.
Home-page: UNKNOWN
Author: Andreas Svela
Author-email: asvela@ic.ac.uk
License: MIT
Project-URL: Documentation, https://keyoscacquire.readthedocs.io/
Project-URL: Source, https://github.com/asvela/keyoscacquire
Platform: UNKNOWN
Classifier: License :: OSI Approved :: MIT License
Classifier: Programming Language :: Python :: 3
Classifier: Programming Language :: Python :: 3.7
Classifier: Operating System :: Microsoft :: Windows
Requires-Dist: pyvisa
Requires-Dist: argparse
Requires-Dist: numpy
Requires-Dist: matplotlib
Requires-Dist: tqdm
